{
  "format": "unipackage-unibuild-pre1",
  "uses": [
    {
      "package": "meteor"
    },
    {
      "package": "tracker"
    },
    {
      "package": "retry"
    },
    {
      "package": "ddp"
    },
    {
      "package": "mongo"
    },
    {
      "package": "underscore"
    },
    {
      "package": "http"
    },
    {
      "package": "random"
    }
  ],
  "resources": [
    {
      "type": "prelink",
      "file": "web.cordova-legacy/packages/autoupdate.js",
      "length": 8563,
      "offset": 0,
      "servePath": "/packages/autoupdate.js"
    }
  ],
  "packageVariables": [
    {
      "name": "Autoupdate",
      "export": true
    },
    {
      "name": "ClientVersions"
    }
  ]
}